{
  "meta": {
    "session": "asia",
    "session_label": "Asia Pre-Session",
    "session_window_utc": "23:00-08:00",
    "generated_at_utc": "2026-07-18T04:07:49.794514+00:00",
    "generated_at_display_tz": "2026-07-18T09:37:49.794514+05:30",
    "display_timezone": "Asia/Kolkata"
  },
  "macro": {
    "ok": true,
    "reason": null,
    "high_impact_next_window": [],
    "all_upcoming_next_window": [],
    "window_hours": 24
  },
  "instruments": {
    "NQ": {
      "ok": true,
      "ticker_used": "NQ=F",
      "last_price": 28768.25,
      "prior_day_high": 29797.0,
      "prior_day_low": 29078.5,
      "prior_day_close": 29225.75,
      "pct_change_vs_prior_close": -1.565400374669598,
      "htf_trend_ema8_vs_ema21": "down",
      "swing_high_liquidity_pool": 29050.25,
      "swing_low_liquidity_pool": 28408.25,
      "fair_value_gaps": {
        "bullish_fvg": {
          "gap_low": 28956.0,
          "gap_high": 28960.5
        },
        "bearish_fvg": {
          "gap_low": 28754.5,
          "gap_high": 28756.0
        }
      },
      "bias": "bearish",
      "gamma_data": {
        "available": true,
        "spot": 19850,
        "call_wall": 19900,
        "put_wall": 19700,
        "gamma_flip": 19800,
        "net_gex": "+1.2B",
        "max_pain": 19800,
        "top_oi": "19800C (exp 2026-07-18), 19700P (exp 2026-07-18)"
      }
    },
    "DXY": {
      "ok": true,
      "ticker_used": "DX-Y.NYB",
      "last_price": 100.75499725341797,
      "prior_day_high": 100.83000183105469,
      "prior_day_low": 100.44000244140625,
      "prior_day_close": 100.7300033569336,
      "pct_change_vs_prior_close": 0.024812762485284464,
      "htf_trend_ema8_vs_ema21": "down",
      "swing_high_liquidity_pool": 100.86699676513672,
      "swing_low_liquidity_pool": 100.7040023803711,
      "fair_value_gaps": {
        "bullish_fvg": {
          "gap_low": 100.74400329589844,
          "gap_high": 100.75399780273438
        },
        "bearish_fvg": {
          "gap_low": 100.74400329589844,
          "gap_high": 100.74600219726562
        }
      },
      "bias": "neutral",
      "gamma_data": {
        "available": false,
        "note": "DXY has no reliable options/gamma chain (thin ICE DX options market) - price action + macro/news only, by design."
      }
    },
    "GC": {
      "ok": true,
      "ticker_used": "GC=F",
      "last_price": 4023.0,
      "prior_day_high": 4030.5,
      "prior_day_low": 3972.60009765625,
      "prior_day_close": 3985.60009765625,
      "pct_change_vs_prior_close": 0.938375688161569,
      "htf_trend_ema8_vs_ema21": "down",
      "swing_high_liquidity_pool": 4028.89990234375,
      "swing_low_liquidity_pool": 3963.0,
      "fair_value_gaps": {
        "bullish_fvg": {
          "gap_low": 4017.10009765625,
          "gap_high": 4017.5
        },
        "bearish_fvg": {
          "gap_low": 4011.300048828125,
          "gap_high": 4011.60009765625
        }
      },
      "bias": "neutral",
      "gamma_data": {
        "available": true,
        "spot": 2415,
        "call_wall": 2430,
        "put_wall": 2390,
        "gamma_flip": 2410,
        "net_gex": "-300M",
        "max_pain": 2410,
        "top_oi": "2430C (exp 2026-07-18), 2400P (exp 2026-07-18)"
      }
    }
  },
  "yields": {
    "TNX": {
      "ok": true,
      "last_yield": 4.540999889373779,
      "prev_yield": 4.568999767303467,
      "direction": "falling"
    }
  },
  "confluence_notes": [
    "10Y yield FALLING -> tailwind for Gold and NQ/growth, headwind for DXY.",
    "DXY and Gold biases are inversely aligned (normal relationship) - supports higher-confidence conviction on both."
  ],
  "final_stance": "NEUTRAL / WAIT - mixed signals, let price confirm"
}